mov_cli_jellyplex/__init__.py
mov_cli_jellyplex/jellyfin/scraper.py
mov_cli_jellyplex/plex/scraper.py
mov_cli_jellyplex-1.1.3.dist-info/LICENSE
mov_cli_jellyplex-1.1.3.dist-info/METADATA
mov_cli_jellyplex-1.1.3.dist-info/WHEEL
mov_cli_jellyplex-1.1.3.dist-info/top_level.txt
mov_cli_jellyplex-1.1.3.dist-info/RECORD
