Metadata-Version: 2.2
Name: mov-cli-jellyplex
Version: 1.1.3
Summary: A mov-cli v4 plugin for watching content from your media server.
Author-email: Ananas <ananas@ananas.moe>
License: MIT License
Project-URL: GitHub, https://github.com/mov-cli/mov-cli-jellyplex
Project-URL: BugTracker, https://github.com/mov-cli/mov-cli-jellyplex/issues
Keywords: mov-cli,jellyfin cli,plex cli
Classifier: Operating System :: Microsoft :: Windows :: Windows 11
Classifier: Operating System :: Microsoft :: Windows :: Windows 10
Classifier: Operating System :: POSIX :: Linux
Classifier: License :: OSI Approved :: MIT License
Classifier: Programming Language :: Python :: 3.8
Classifier: Programming Language :: Python :: 3.9
Classifier: Programming Language :: Python :: 3.10
Classifier: Programming Language :: Python :: 3.11
Classifier: Programming Language :: Python :: 3.12
Requires-Python: >=3.8
License-File: LICENSE
Requires-Dist: requests
Requires-Dist: importlib-metadata; python_version < "3.8"
Requires-Dist: plexapi
Provides-Extra: dev
Requires-Dist: ruff; extra == "dev"
Requires-Dist: build; extra == "dev"
